dng_logger/__init__.py
dng_logger/logger.py
dng_logger/writeConfig.py
dng_logger-1.0.1.dist-info/LICENSE
dng_logger-1.0.1.dist-info/METADATA
dng_logger-1.0.1.dist-info/WHEEL
dng_logger-1.0.1.dist-info/top_level.txt
dng_logger-1.0.1.dist-info/RECORD
